datascope-0.0.6.dist-info/WHEEL
datascope-0.0.6.dist-info/top_level.txt
datascope-0.0.6.dist-info/LICENSE
datascope-0.0.6.dist-info/RECORD
datascope-0.0.6.dist-info/METADATA
datascope/debugger/debugger.py
datascope/debugger/__init__.py
datascope/importance/common.py
datascope/importance/importance.py
datascope/importance/add.py
datascope/importance/shapley.py
datascope/importance/__init__.py
datascope/importance/shapley_cy.cpython-38-i386-linux-gnu.so
