Metadata-Version: 2.1
Name: datascope
Version: 0.0.6
Summary: Measuring data importance over ML pipelines using the Shapley value.
Home-page: https://ease.ml/datascope/
Author-email: easeml@ds3lab.com
License: MIT
License-File: LICENSE
Requires-Dist: numpy (>=1.21)
Requires-Dist: scikit-learn (>=1.0)
Requires-Dist: scipy (>=1.7)
Requires-Dist: pandas (>=1.3)
Requires-Dist: matplotlib (>=3.5)
Requires-Dist: PyYAML (>=6.0)
Requires-Dist: tqdm (>=4.62)
Requires-Dist: setuptools
Requires-Dist: zerorpc (>=0.6.3)
Provides-Extra: complete
Requires-Dist: pytest-benchmark (>=3.4) ; extra == 'complete'
Requires-Dist: wheel ; extra == 'complete'
Requires-Dist: flake8 (>=4.0) ; extra == 'complete'
Requires-Dist: pytest-cov (>=3.0) ; extra == 'complete'
Requires-Dist: build (>=0.9) ; extra == 'complete'
Requires-Dist: black ; extra == 'complete'
Requires-Dist: cython (>=0.29) ; extra == 'complete'
Requires-Dist: numpy (>=1.21) ; extra == 'complete'
Requires-Dist: twine (>=4.0) ; extra == 'complete'
Requires-Dist: jupyterlab (>=3.3) ; extra == 'complete'
Requires-Dist: types-PyYAML (>=6.0) ; extra == 'complete'
Requires-Dist: pytest (>=6.2) ; extra == 'complete'
Requires-Dist: mypy (>=0.9) ; extra == 'complete'
Provides-Extra: dev
Requires-Dist: mypy (>=0.9) ; extra == 'dev'
Requires-Dist: flake8 (>=4.0) ; extra == 'dev'
Requires-Dist: pytest (>=6.2) ; extra == 'dev'
Requires-Dist: pytest-benchmark (>=3.4) ; extra == 'dev'
Requires-Dist: pytest-cov (>=3.0) ; extra == 'dev'
Requires-Dist: black ; extra == 'dev'
Requires-Dist: types-PyYAML (>=6.0) ; extra == 'dev'
Requires-Dist: cython (>=0.29) ; extra == 'dev'
Requires-Dist: jupyterlab (>=3.3) ; extra == 'dev'
Requires-Dist: twine (>=4.0) ; extra == 'dev'
Requires-Dist: build (>=0.9) ; extra == 'dev'
Requires-Dist: numpy (>=1.21) ; extra == 'dev'
Requires-Dist: wheel ; extra == 'dev'
